{
  "type": "directory",
  "name": "",
  "children": [
    {
      "type": "directory",
      "name": "docs",
      "children": [
        {
          "type": "file",
          "name": "a.txt",
          "content": "This is a text file.",
          "modified": "2023-10-01T12:00:00Z"
        },
        {
          "type": "file",
          "name": "b.txt",
          "content": "This is another text file.",
          "modified": "2023-10-01T12:00:00Z"
        }
      ],
      "modified": "2023-10-01T12:00:00Z"
    },
    {
      "type": "file",
      "name": "readme.md",
      "content": "# Welcome to the Project\n\nThis is a sample project structure.\n\n## Contents\n- `docs/`: Contains documentation files.\n- `readme.md`: This file provides an overview of the project.\n",
      "modified": "2023-10-01T12:00:00Z"
    }
  ],
  "modified": "2023-10-01T12:00:00Z"
}
